README.md
setup.py
bin/get_test_jwt_token
bin/klue_config
bin/run_acceptance_tests
klue_microservice/__init__.py
klue_microservice/api.py
klue_microservice/auth.py
klue_microservice/config.py
klue_microservice/crash.py
klue_microservice/crash.yaml
klue_microservice/exceptions.py
klue_microservice/gunicorn.py
klue_microservice/log.py
klue_microservice/ping.yaml
klue_microservice/test.py
klue_microservice/utils.py
klue_microservice.egg-info/PKG-INFO
klue_microservice.egg-info/SOURCES.txt
klue_microservice.egg-info/dependency_links.txt
klue_microservice.egg-info/not-zip-safe
klue_microservice.egg-info/requires.txt
klue_microservice.egg-info/top_level.txt
test/test_crash_handler.py
test/test_ping_api.py
test/testserver.py