Metadata-Version: 1.1
Name: klue-microservice
Version: 0.0.119
Summary: Easily implement a REST API and deploy it as a Docker container on amazon AWS
Home-page: https://github.com/erwan-lemonnier/klue-microservice
Author: Erwan Lemonnier
Author-email: erwan@lemonnier.se
License: BSD
Platform: any
Classifier: Environment :: Web Environment
Classifier: Intended Audience :: Developers
Classifier: License :: OSI Approved :: BSD License
Classifier: Operating System :: OS Independent
Classifier: Programming Language :: Python
Classifier: Topic :: Internet :: WWW/HTTP :: Dynamic Content
Classifier: Topic :: Software Development :: Libraries :: Python Modules
